cosmo/__init__.py
cosmo/app.py
cosmo/error.py
cosmo/html_page.py
cosmo/request.py
cosmo/response.py
cosmo/route.py
cosmo/router.py
cosmo/ssl.py
cosmo/status_codes.py
cosmo-0.7.0.dist-info/METADATA
cosmo-0.7.0.dist-info/WHEEL
cosmo-0.7.0.dist-info/RECORD
