Metadata-Version: 2.1
Name: cosmo
Version: 0.7.0
Summary: A high-level web server with fine tuned low-level control.
Home-page: https://github.com/kronifer/cosmo
License: Apache-2.0
Author: Kronifer
Author-email: 44979306+Kronifer@users.noreply.github.com
Requires-Python: >=3.8,<4.0
Classifier: License :: OSI Approved :: Apache Software License
Classifier: Programming Language :: Python :: 3
Classifier: Programming Language :: Python :: 3.8
Classifier: Programming Language :: Python :: 3.9
Classifier: Programming Language :: Python :: 3.10
Classifier: Programming Language :: Python :: 3.11
Provides-Extra: uvloop
Requires-Dist: isort (>=5.10.1,<6.0.0)
Requires-Dist: loguru (>=0.5.3,<0.6.0)
